{
  "context-menu": {
    "atom-text-editor": [
      {
        "label": "Run with Behat",
        "command": "behat-tools:run"
      }
    ]
  },
  "menu": [
    {
      "label": "Selection",
      "submenu": [
        {
          "label": "Run with Behat",
          "command": "behat-tools:run"
        }
      ]
    },
    {
      "label": "Packages",
      "submenu": [
        {
          "label": "Behat Tools",
          "submenu": [
            {
              "label": "Run/Run Selection",
              "command": "behat-tools:run"
            },
            {
              "label": "Find Command",
              "command": "behat-tools:findCommand"
            }
          ]
        }
      ]
    }

  ]
}
